spank/__init__.py
spank/functions.py
spank/spank.py
spank-0.0.1.dist-info/METADATA
spank-0.0.1.dist-info/WHEEL
spank-0.0.1.dist-info/top_level.txt
spank-0.0.1.dist-info/RECORD
