Metadata-Version: 2.1
Name: spank
Version: 0.0.1
Summary: Swarm Intelligence in Python
Home-page: https://github.com/guofei9987/spank
Author: Guo Fei
Author-email: guofei9987@foxmail.com
License: MIT
Platform: linux
Platform: windows
Platform: macos
Requires-Python: >=3.5
Requires-Dist: numpy
Requires-Dist: pandas
